surykatka/__init__.py
surykatka/bot.py
surykatka/cli.py
surykatka/configuration.py
surykatka/db.py
surykatka/dns.py
surykatka/domain.py
surykatka/http.py
surykatka/network.py
surykatka/platform.py
surykatka/ssl.py
surykatka/status.py
surykatka-0.8.0.dist-info/COPYING
surykatka-0.8.0.dist-info/METADATA
surykatka-0.8.0.dist-info/WHEEL
surykatka-0.8.0.dist-info/entry_points.txt
surykatka-0.8.0.dist-info/top_level.txt
surykatka-0.8.0.dist-info/zip-safe
surykatka-0.8.0.dist-info/RECORD
