Metadata-Version: 2.1
Name: surykatka
Version: 0.8.0
Author: Nexedi
Author-email: romain@nexedi.com
License: GPLv3+
Requires-Python: >=3.5
License-File: COPYING
Requires-Dist: setuptools (>40.5.0)
Requires-Dist: requests (>2.20.0)
Requires-Dist: forcediphttpsadapter
Requires-Dist: peewee (>2.10.1)
Requires-Dist: click (>=7.0)
Requires-Dist: dnspython
Requires-Dist: python-whois
Requires-Dist: miniupnpc
Provides-Extra: dev
Requires-Dist: pytest ; extra == 'dev'
Requires-Dist: black ; extra == 'dev'
Requires-Dist: pyflakes ; extra == 'dev'
Requires-Dist: mock ; extra == 'dev'
Requires-Dist: httpretty ; extra == 'dev'
